zammad_pgp_import/__init__.py
zammad_pgp_import/exceptions.py
zammad_pgp_import/pgp.py
zammad_pgp_import/utils.py
zammad_pgp_import/zammad.py
zammad_pgp_import-0.2.0.dist-info/LICENSE
zammad_pgp_import-0.2.0.dist-info/METADATA
zammad_pgp_import-0.2.0.dist-info/WHEEL
zammad_pgp_import-0.2.0.dist-info/entry_points.txt
zammad_pgp_import-0.2.0.dist-info/RECORD
