Metadata-Version: 2.3
Name: zammad-pgp-import
Version: 0.2.0
Summary: 
Author: kmille
Author-email: github@androidloves.me
Requires-Python: >=3.10
Classifier: Programming Language :: Python :: 3
Classifier: Programming Language :: Python :: 3.10
Classifier: Programming Language :: Python :: 3.11
Classifier: Programming Language :: Python :: 3.12
Classifier: Programming Language :: Python :: 3.13
Requires-Dist: flask (>=3.1.1,<4.0.0)
Requires-Dist: flask-basicauth (>=0.2.0,<0.3.0)
Requires-Dist: mypy (>=1.16.1,<2.0.0)
Requires-Dist: requests (>=2.32.4,<3.0.0)
Requires-Dist: waitress (>=3.0.2,<4.0.0)
